fastapi_restify/__init__.py
fastapi_restify/file_database.py
fastapi_restify/mongo_database.py
fastapi_restify/response_models.py
fastapi_restify/restful_app.py
fastapi_restify/restful_router.py
fastapi_restify/uvicorn_server_context.py
fastapi_restify/web_server.py
fastapi_restify-0.0.4.dist-info/LICENSE
fastapi_restify-0.0.4.dist-info/METADATA
fastapi_restify-0.0.4.dist-info/WHEEL
fastapi_restify-0.0.4.dist-info/top_level.txt
fastapi_restify-0.0.4.dist-info/RECORD
