Metadata-Version: 2.1
Name: fastapi-restify
Version: 0.0.4
Summary: Rest API configured with pydantic, backed by file database or mongo
Home-page: https://github.com/syntithenai/fastapi_restify
Author: Steve Ryan
Author-email: syntithenai@gmail.com
License: MIT
Platform: UNKNOWN
Classifier: License :: OSI Approved :: MIT License
Classifier: Programming Language :: Python :: 3
Classifier: Programming Language :: Python :: 3.7
License-File: LICENSE
Requires-Dist: motor
Requires-Dist: PyJWT
Requires-Dist: bcrypt
Requires-Dist: uvicorn
Requires-Dist: pymongo
Requires-Dist: python-decouple
Requires-Dist: fastapi
Requires-Dist: pydantic[email]
Requires-Dist: passlib
Requires-Dist: pytest
Requires-Dist: jinja2
Requires-Dist: aiofiles
Requires-Dist: requests
Requires-Dist: pymongo-inmemory
